fairyfly_therm_standards/__init__.py
fairyfly_therm_standards/conditions/Default.xml
fairyfly_therm_standards/gases/Default.xml
fairyfly_therm_standards/materials/Default.xml
fairyfly_therm_standards-0.1.0.dist-info/licenses/LICENSE
fairyfly_therm_standards-0.1.0.dist-info/METADATA
fairyfly_therm_standards-0.1.0.dist-info/WHEEL
fairyfly_therm_standards-0.1.0.dist-info/top_level.txt
fairyfly_therm_standards-0.1.0.dist-info/RECORD
